araucanaxai/__init__.py
araucanaxai/constants.py
araucanaxai/init.py
araucanaxai/utils.py
araucanaxai-0.9.4.dist-info/LICENSE
araucanaxai-0.9.4.dist-info/METADATA
araucanaxai-0.9.4.dist-info/WHEEL
araucanaxai-0.9.4.dist-info/top_level.txt
araucanaxai-0.9.4.dist-info/RECORD
