Metadata-Version: 2.1
Name: araucanaxai
Version: 0.9.4
Summary: A novel approach for generating explanations of the predictions of a generic ML model
Home-page: https://github.com/detsutut/AraucanaXAI
Author: Tommaso Buonocore
Author-email: buonocore.tms@gmail.com
License: UNKNOWN
Project-URL: Bug Tracker, https://github.com/detsutut/AraucanaXAI/issues
Keywords: xai,ai
Platform: UNKNOWN
Classifier: Programming Language :: Python :: 3
Classifier: License :: OSI Approved :: MIT License
Classifier: Operating System :: OS Independent
Requires-Python: >=3.6
License-File: LICENSE
Requires-Dist: gower
Requires-Dist: pandas
Requires-Dist: numpy
Requires-Dist: scikit-learn
Requires-Dist: imblearn
